{
  "trace_id": "sandbox-609c4fc7-3507",
  "session_id": "sess-20260528-nba2",
  "kind": "prop",
  "player": "Shai Gilgeous-Alexander",
  "prop_type": "pts",
  "line": 29.5,
  "game_date": "2026-05-28",
  "home_team": "San Antonio Spurs",
  "away_team": "Oklahoma City Thunder",
  "recommendation": "under",
  "odds": -120,
  "edge_pct": 21.35,
  "recommended_units": 1.0,
  "confidence_tier": "RESEARCH_CANDIDATE",
  "null_fields": [],
  "full_result": {
    "player_name": "Shai Gilgeous-Alexander",
    "league": "NBA",
    "prop_type": "pts",
    "line": 29.5,
    "status": "success",
    "skip_reason": null,
    "missing_requirements": [],
    "over_prob": 0.241,
    "under_prob": 0.759,
    "projection_mean": 25.8877,
    "projection_std": 5.2487,
    "projection_p10": 19.1754,
    "projection_p50": 25.9326,
    "projection_p90": 32.5491,
    "distribution_type": "normal",
    "edge_over": -28.28,
    "edge_under": 21.35,
    "recommendation": "under",
    "confidence_tier": "A",
    "kelly_fraction": 0.2349,
    "recommended_units": 5.0,
    "bet_side_odds": -120.0,
    "notes": [],
    "imputed_fraction": 0.0,
    "over_calibration_audit": {
      "raw_prob": 0.241,
      "calibrated_prob": 0.241,
      "league": "NBA",
      "plane": "prop",
      "market": "over",
      "method_resolved": null,
      "profile_id": null,
      "context_slice": "playoff",
      "resolved_slice": null,
      "path": "static_identity"
    },
    "under_calibration_audit": {
      "raw_prob": 0.759,
      "calibrated_prob": 0.759,
      "league": "NBA",
      "plane": "prop",
      "market": "under",
      "method_resolved": null,
      "profile_id": null,
      "context_slice": "playoff",
      "resolved_slice": null,
      "path": "static_identity"
    },
    "context_source": "provided",
    "baseline_used": false,
    "simulation_distributions": [
      {
        "target": "player_stat",
        "market": "player_prop",
        "stat_key": "pts",
        "distribution_type": "normal",
        "distribution_params": {
          "mu": 25.919999999999998,
          "sigma": 5.279999999999999
        },
        "params_schema_version": 1,
        "sample_mean": 25.887660674110055,
        "sample_std": 5.248744132227395,
        "p10": 19.1754355067409,
        "p50": 25.93264950535159,
        "p90": 32.54911816662192,
        "n_iterations": 10000,
        "seed": 3342242023,
        "context_hash": "d581e71e",
        "component_version": "player_prop_fast_v1"
      }
    ]
  }
}